EXgen/EXgen.py
EXgen/__init__.py
EXgen/templates/homework_template.tex
EXgen/templates/figures/TUG_logo.eps
EXgen/templates/figures/igte_logo.eps
EXgen/templates/sampleproject/config.yaml
EXgen/templates/sampleproject/tasks.tex
EXgen/templates/sampleproject/nets/schematic_1_1.net
EXgen/templates/sampleproject/nets/schematic_1_2.net
EXgen/templates/sampleproject/nets/schematic_1_3.net
EXgen/templates/sampleproject/nets/schematic_1_4.net
EXgen/templates/sampleproject/nets/schematic_2_1.net
EXgen/templates/sampleproject/nets/schematic_2_2.net
EXgen/templates/sampleproject/nets/schematic_2_3.net
EXgen/templates/sampleproject/nets/schematic_2_4.net
EXgen/util/__init__.py
EXgen/util/expression_handler.py
EXgen/util/solver_functions.py
EXgen/util/util.py
EXgen-0.1.7.data/scripts/exgen
EXgen-0.1.7.dist-info/LICENSE
EXgen-0.1.7.dist-info/METADATA
EXgen-0.1.7.dist-info/WHEEL
EXgen-0.1.7.dist-info/top_level.txt
EXgen-0.1.7.dist-info/RECORD
